urdfeus/__init__.py
urdfeus/common.py
urdfeus/compatibility.py
urdfeus/grouping_joint.py
urdfeus/mesh2eus.py
urdfeus/mesh_cache.py
urdfeus/read_yaml.py
urdfeus/urdf2eus.py
urdfeus/apps/__init__.py
urdfeus/apps/mesh2eus.py
urdfeus/apps/urdf2eus.py
urdfeus/templates/__init__.py
urdfeus/templates/euscollada-robot.l
urdfeus/templates/urdf_template.py
urdfeus-1.1.10.dist-info/licenses/LICENSE
urdfeus-1.1.10.dist-info/METADATA
urdfeus-1.1.10.dist-info/WHEEL
urdfeus-1.1.10.dist-info/entry_points.txt
urdfeus-1.1.10.dist-info/top_level.txt
urdfeus-1.1.10.dist-info/RECORD
