Metadata-Version: 2.4
Name: urdfeus
Version: 1.1.10
Summary: URDF converter for Euslisp
Author-email: Iori Yanokura <yanokura@jsk.imi.i.u-tokyo.ac.jp>
License: Copyright (c) 2023 Iori Yanokura.
Project-URL: Homepage, https://github.com/iory/urdfeus
Project-URL: Repository, https://github.com/iory/urdfeus
Keywords: urdf,euslisp
Classifier: Programming Language :: Python :: 3
Classifier: License :: OSI Approved :: MIT License
Classifier: Operating System :: OS Independent
License-File: LICENSE
Requires-Dist: pyyaml
Requires-Dist: scikit-robot>=0.0.35
Provides-Extra: all
Requires-Dist: open3d; extra == "all"
Dynamic: license-file
